README.txt
setup.py
expel/__init__.py
expel.message.egg-info/PKG-INFO
expel.message.egg-info/SOURCES.txt
expel.message.egg-info/dependency_links.txt
expel.message.egg-info/namespace_packages.txt
expel.message.egg-info/requires.txt
expel.message.egg-info/top_level.txt
expel/message/__init__.py
expel/message/xmessage.py
expel/message/xmessageparser.py
expel/message/xpl.py