Metadata-Version: 1.0
Name: expel.message
Version: 0.2
Summary: expel.message is part of the expel namespace package and
Home-page: http://www.sffjunkie.co.uk/python-expel.html
Author: Simon Kennedy
Author-email: code@sffjunkie.co.uk
License: Apache-2.0
Platform: UNKNOWN
